stupid_dns_watchdog/__init__.py
stupid_dns_watchdog/main.py
stupid_dns_watchdog/src/__init__.py
stupid_dns_watchdog-0.0.1.dist-info/LICENSE
stupid_dns_watchdog-0.0.1.dist-info/METADATA
stupid_dns_watchdog-0.0.1.dist-info/WHEEL
stupid_dns_watchdog-0.0.1.dist-info/entry_points.txt
stupid_dns_watchdog-0.0.1.dist-info/top_level.txt
stupid_dns_watchdog-0.0.1.dist-info/RECORD
