Metadata-Version: 2.1
Name: stupid-dns-watchdog
Version: 0.0.1
Summary: Watchdog for changes in your external IP. Automatically pushes the changes to git.
Home-page: https://github.com/Velythyl/stupid-dns-watchdog
Author: Charlie Gauthier
Author-email: charlie.gauthier@umontreal.ca
License: MIT
Platform: UNKNOWN
License-File: LICENSE
Requires-Dist: python-crontab
